pyglotaran_extras/__init__.py
pyglotaran_extras/types.py
pyglotaran_extras/config/__init__.py
pyglotaran_extras/config/config.py
pyglotaran_extras/config/plot_config.py
pyglotaran_extras/config/utils.py
pyglotaran_extras/deprecation/__init__.py
pyglotaran_extras/deprecation/deprecation_utils.py
pyglotaran_extras/inspect/__init__.py
pyglotaran_extras/inspect/a_matrix.py
pyglotaran_extras/inspect/utils.py
pyglotaran_extras/io/__init__.py
pyglotaran_extras/io/load_data.py
pyglotaran_extras/io/setup_case_study.py
pyglotaran_extras/io/utils.py
pyglotaran_extras/plotting/__init__.py
pyglotaran_extras/plotting/plot_coherent_artifact.py
pyglotaran_extras/plotting/plot_concentrations.py
pyglotaran_extras/plotting/plot_data.py
pyglotaran_extras/plotting/plot_doas.py
pyglotaran_extras/plotting/plot_guidance.py
pyglotaran_extras/plotting/plot_irf_dispersion_center.py
pyglotaran_extras/plotting/plot_overview.py
pyglotaran_extras/plotting/plot_pfid.py
pyglotaran_extras/plotting/plot_residual.py
pyglotaran_extras/plotting/plot_spectra.py
pyglotaran_extras/plotting/plot_svd.py
pyglotaran_extras/plotting/plot_traces.py
pyglotaran_extras/plotting/style.py
pyglotaran_extras/plotting/utils.py
pyglotaran_extras-0.7.4.dist-info/METADATA
pyglotaran_extras-0.7.4.dist-info/WHEEL
pyglotaran_extras-0.7.4.dist-info/licenses/LICENSE
pyglotaran_extras-0.7.4.dist-info/RECORD
