Metadata-Version: 2.4
Name: pyglotaran-extras
Version: 0.7.4
Summary: Supplementary package for pyglotaran with (example) plotting code.
Project-URL: Changelog, https://pyglotaran-extras.readthedocs.io/en/latest/changelog.html
Project-URL: Documentation, https://pyglotaran-extras.readthedocs.io
Project-URL: GloTarAn Ecosystem, https://glotaran.org
Project-URL: Homepage, https://github.com/glotaran/pyglotaran-extras
Project-URL: Source, https://github.com/glotaran/pyglotaran-extras
Project-URL: Tracker, https://github.com/glotaran/pyglotaran-extras/issues
Author-email: Joris Snellenburg <j.snellenburg@gmail.com>, Sebastian Weigand <s.weigand.phy@gmail.com>
License: The MIT License (MIT)
License-File: LICENSE
Classifier: Development Status :: 4 - Beta
Classifier: Intended Audience :: Science/Research
Classifier: License :: OSI Approved :: MIT License
Classifier: Natural Language :: English
Classifier: Operating System :: OS Independent
Classifier: Programming Language :: Python :: 3 :: Only
Classifier: Programming Language :: Python :: 3.10
Classifier: Programming Language :: Python :: 3.11
Classifier: Programming Language :: Python :: 3.12
Classifier: Programming Language :: Python :: 3.13
Classifier: Programming Language :: Python :: 3.14
Classifier: Topic :: Scientific/Engineering
Classifier: Topic :: Scientific/Engineering :: Chemistry
Classifier: Topic :: Scientific/Engineering :: Physics
Requires-Python: >=3.10
Requires-Dist: cycler>=0.10
Requires-Dist: docstring-parser>=0.16
Requires-Dist: matplotlib>=3.3
Requires-Dist: numpy>=1.22
Requires-Dist: packaging>=23.1
Requires-Dist: pydantic>=2.7
Requires-Dist: pyglotaran>=0.7
Requires-Dist: ruamel-yaml>=0.18.6
Requires-Dist: tabulate>=0.8.9
Requires-Dist: xarray>=2022.3
Provides-Extra: dev
Requires-Dist: autodoc-pydantic>=2.2; extra == 'dev'
Requires-Dist: coverage[toml]; extra == 'dev'
Requires-Dist: jsonschema>=4.22; extra == 'dev'
Requires-Dist: jupyterlab>=3; extra == 'dev'
Requires-Dist: myst-nb>=1.1.1; extra == 'dev'
Requires-Dist: myst-parser>=0.12; extra == 'dev'
Requires-Dist: nbval>=0.9.6; extra == 'dev'
Requires-Dist: numpydoc>=0.8; extra == 'dev'
Requires-Dist: pluggy>=0.7; extra == 'dev'
Requires-Dist: pydata-sphinx-theme>=0.16.1; extra == 'dev'
Requires-Dist: pytest-cov>=2.5.1; extra == 'dev'
Requires-Dist: pytest>=3.7.1; extra == 'dev'
Requires-Dist: sphinx-copybutton>=0.3; extra == 'dev'
Requires-Dist: sphinx-last-updated-by-git>=0.3; extra == 'dev'
Requires-Dist: sphinx>=3.2; extra == 'dev'
Requires-Dist: sphinxcontrib-mermaid>=0.9.2; extra == 'dev'
Provides-Extra: docs
Requires-Dist: autodoc-pydantic>=2.2; extra == 'docs'
Requires-Dist: jupyterlab>=3; extra == 'docs'
Requires-Dist: myst-nb>=1.1.1; extra == 'docs'
Requires-Dist: myst-parser>=0.12; extra == 'docs'
Requires-Dist: numpydoc>=0.8; extra == 'docs'
Requires-Dist: pydata-sphinx-theme>=0.16.1; extra == 'docs'
Requires-Dist: sphinx-copybutton>=0.3; extra == 'docs'
Requires-Dist: sphinx-last-updated-by-git>=0.3; extra == 'docs'
Requires-Dist: sphinx>=3.2; extra == 'docs'
Requires-Dist: sphinxcontrib-mermaid>=0.9.2; extra == 'docs'
Provides-Extra: test
Requires-Dist: coverage[toml]; extra == 'test'
Requires-Dist: jsonschema>=4.22; extra == 'test'
Requires-Dist: nbval>=0.9.6; extra == 'test'
Requires-Dist: pluggy>=0.7; extra == 'test'
Requires-Dist: pytest-cov>=2.5.1; extra == 'test'
Requires-Dist: pytest>=3.7.1; extra == 'test'
